configmate_plugins/yaml_parser/__init__.py
configmate_plugins/yaml_parser/yaml_parser.py
configmate_yamlparser-0.1.1.dist-info/METADATA
configmate_yamlparser-0.1.1.dist-info/WHEEL
configmate_yamlparser-0.1.1.dist-info/RECORD
